latentforce/__init__.py
latentforce/agentforce.py
latentforce/config.py
latentforce/logger.py
latentforce/modelforce.py
latentforce-0.5.0.dist-info/METADATA
latentforce-0.5.0.dist-info/WHEEL
latentforce-0.5.0.dist-info/licenses/LICENSE
latentforce-0.5.0.dist-info/RECORD
