Metadata-Version: 2.3
Name: latentforce
Version: 0.5.0
Summary: Python client for LatentForce.ai
Project-URL: Homepage, https://www.latentforce.ai
Project-URL: Documentation, https://www.latentforce.ai
Project-URL: Repository, https://www.latentforce.ai
Author-email: Aravind Jayendran <aravind@latantforce.ai>
Maintainer-email: Aravind Jayendran <aravind@latantforce.ai>
License:                                  Apache License
License-File: LICENSE
Keywords: Agents,LatentForce.ai,Models,Python-Client
Classifier: Development Status :: 4 - Beta
Classifier: Programming Language :: Python
Requires-Python: >=3.8
Requires-Dist: openai
Requires-Dist: requests
